{
  "predicate": "m297004",
  "inner": {
    "queries": [],
    "pagination": null,
    "next": {
      "rule": 26,
      "head_index": 2,
      "children": [
        {
          "queries": [],
          "pagination": null,
          "next": {
            "rule": 82,
            "head_index": 0,
            "children": [
              {
                "queries": [],
                "pagination": null,
                "next": null
              }
            ]
          }
        }
      ]
    }
  }
}